{
    "04-04-22 04:51:02": [
        {
            "position": "1",
            "titre": "Column 1",
            "taches": [
                {
                    "text": "lutwrld",
                    "date": "2022-04-04",
                    "debut": "12:00",
                    "fin": "13:00",
                    "etat": "init",
                    "parent": "1"
                }
            ]
        },
        {
            "position": "2",
            "titre": "Column 2",
            "taches": []
        },
        {
            "position": "3",
            "titre": "Column 3",
            "taches": []
        },
        [
            {
                "text": "lang",
                "date": "2022-04-04",
                "debut": "10:00",
                "fin": "10:05",
                "etat": "init",
                "parent": "1"
            }
        ]
    ],
    "04-04-22 06:32:24": [
        {
            "position": "1",
            "titre": "Column 1",
            "taches": [
                {
                    "text": "lutwrld",
                    "date": "2022-04-04",
                    "debut": "12:00",
                    "fin": "13:00",
                    "etat": "init",
                    "parent": "1"
                }
            ]
        },
        {
            "position": "2",
            "titre": "Column 2",
            "taches": []
        },
        {
            "position": "3",
            "titre": "Column 3",
            "taches": [
                {
                    "text": "lut wrld is going good",
                    "date": "2022-04-04",
                    "debut": "12:00",
                    "fin": "15:09",
                    "etat": "init",
                    "parent": "3"
                }
            ]
        },
        [
            {
                "text": "lang",
                "date": "2022-04-04",
                "debut": "10:00",
                "fin": "10:05",
                "etat": "init",
                "parent": "1"
            }
        ]
    ],
    "04-04-22 06:32:46": [
        {
            "position": "1",
            "titre": "Column 1",
            "taches": [
                {
                    "text": "lutwrld",
                    "date": "2022-04-04",
                    "debut": "12:00",
                    "fin": "13:00",
                    "etat": "init",
                    "parent": "1"
                }
            ]
        },
        {
            "position": "2",
            "titre": "nice",
            "taches": [
                {
                    "text": "nice",
                    "date": "",
                    "debut": "",
                    "fin": "",
                    "etat": "init",
                    "parent": "2"
                }
            ]
        },
        {
            "position": "3",
            "titre": "Column 3",
            "taches": [
                {
                    "text": "lut wrld is going good",
                    "date": "2022-04-04",
                    "debut": "12:00",
                    "fin": "15:09",
                    "etat": "init",
                    "parent": "3"
                }
            ]
        },
        [
            {
                "text": "lang",
                "date": "2022-04-04",
                "debut": "10:00",
                "fin": "10:05",
                "etat": "init",
                "parent": "1"
            }
        ]
    ],
    "04-04-22 06:48:23": [
        {
            "position": "1",
            "titre": "Column 1",
            "taches": [
                {
                    "text": "lutwrld",
                    "date": "2022-04-04",
                    "debut": "12:00",
                    "fin": "13:00",
                    "etat": "init",
                    "parent": "1"
                }
            ]
        },
        {
            "position": "2",
            "titre": "nice",
            "taches": []
        },
        {
            "position": "3",
            "titre": "Column 3",
            "taches": []
        },
        [
            {
                "text": "lang",
                "date": "2022-04-04",
                "debut": "10:00",
                "fin": "10:05",
                "etat": "init",
                "parent": "1"
            },
            {
                "text": "nice",
                "date": "",
                "debut": "",
                "fin": "",
                "etat": "init",
                "parent": "2"
            },
            {
                "text": "lut wrld is going good",
                "date": "2022-04-04",
                "debut": "12:00",
                "fin": "15:09",
                "etat": "init",
                "parent": "3"
            }
        ]
    ],
    "04-04-22 06:49:54": [
        {
            "position": "1",
            "titre": "the",
            "taches": [
                {
                    "text": "lutwrld",
                    "date": "2022-04-04",
                    "debut": "12:00",
                    "fin": "13:00",
                    "etat": "init",
                    "parent": "1"
                }
            ]
        },
        {
            "position": "2",
            "titre": "end",
            "taches": [
                {
                    "text": "is",
                    "date": "",
                    "debut": "",
                    "fin": "",
                    "etat": "init",
                    "parent": "2"
                }
            ]
        },
        {
            "position": "3",
            "titre": "|^^|",
            "taches": [
                {
                    "text": "wrld",
                    "date": "",
                    "debut": "",
                    "fin": "",
                    "etat": "init",
                    "parent": "3"
                }
            ]
        },
        [
            {
                "text": "lang",
                "date": "2022-04-04",
                "debut": "10:00",
                "fin": "10:05",
                "etat": "init",
                "parent": "1"
            },
            {
                "text": "nice",
                "date": "",
                "debut": "",
                "fin": "",
                "etat": "init",
                "parent": "2"
            },
            {
                "text": "lut wrld is going good",
                "date": "2022-04-04",
                "debut": "12:00",
                "fin": "15:09",
                "etat": "init",
                "parent": "3"
            }
        ]
    ],
    "04-04-22 07:14:49": [
        {
            "position": "1",
            "titre": "the",
            "taches": [
                {
                    "text": "lutwrld",
                    "date": "",
                    "debut": "",
                    "fin": "",
                    "etat": "init",
                    "parent": "1"
                },
                {
                    "text": "is",
                    "date": "",
                    "debut": "",
                    "fin": "",
                    "etat": "init",
                    "parent": "1"
                },
                {
                    "text": "the ",
                    "date": "",
                    "debut": "",
                    "fin": "",
                    "etat": "init",
                    "parent": "1"
                },
                {
                    "text": "best\n",
                    "date": "",
                    "debut": "",
                    "fin": "",
                    "etat": "init",
                    "parent": "1"
                },
                {
                    "text": "bets kolomo cjio sko dsko dsok dsok squyb squ qucn cuqc cqun az ez ic cqi cqi cqijc cqijc cqijc cqij cqnjicq cj",
                    "date": "",
                    "debut": "",
                    "fin": "",
                    "etat": "init",
                    "parent": "1"
                },
                {
                    "text": "k,sd ock cxu xl,c qun",
                    "date": "",
                    "debut": "",
                    "fin": "",
                    "etat": "init",
                    "parent": "1"
                }
            ]
        },
        {
            "position": "2",
            "titre": "end",
            "taches": [
                {
                    "text": "ko",
                    "date": "2022-04-04",
                    "debut": "07:12",
                    "fin": "07:13",
                    "etat": "termine",
                    "parent": "2"
                }
            ]
        },
        {
            "position": "3",
            "titre": "|^^|",
            "taches": []
        },
        [
            {
                "text": "lang",
                "date": "2022-04-04",
                "debut": "10:00",
                "fin": "10:05",
                "etat": "init",
                "parent": "1"
            },
            {
                "text": "nice",
                "date": "",
                "debut": "",
                "fin": "",
                "etat": "init",
                "parent": "2"
            },
            {
                "text": "lut wrld is going good",
                "date": "2022-04-04",
                "debut": "12:00",
                "fin": "15:09",
                "etat": "init",
                "parent": "3"
            },
            {
                "text": "lutwrld",
                "date": "2022-04-04",
                "debut": "12:00",
                "fin": "13:00",
                "etat": "init",
                "parent": "1"
            },
            {
                "text": "is",
                "date": "",
                "debut": "",
                "fin": "",
                "etat": "init",
                "parent": "2"
            },
            {
                "text": "wrld",
                "date": "",
                "debut": "",
                "fin": "",
                "etat": "init",
                "parent": "3"
            },
            {
                "text": "lorem ipsum for lut",
                "date": "",
                "debut": "",
                "fin": "",
                "etat": "init",
                "parent": "1"
            },
            {
                "text": "wey",
                "date": "",
                "debut": "",
                "fin": "",
                "etat": "init",
                "parent": "1"
            }
        ]
    ],
    "08-04-22 09:47:58": [
        {
            "position": "1",
            "titre": "Column 1",
            "taches": [
                {
                    "text": "lutwrld",
                    "date": "2022-04-04",
                    "debut": "12:00",
                    "fin": "13:00",
                    "etat": "init",
                    "parent": "1"
                }
            ]
        },
        {
            "position": "2",
            "titre": "Column 2",
            "taches": []
        },
        {
            "position": "3",
            "titre": "Column 3",
            "taches": []
        },
        [
            {
                "text": "lang",
                "date": "2022-04-04",
                "debut": "10:00",
                "fin": "10:05",
                "etat": "init",
                "parent": "1"
            }
        ]
    ],
    "09-04-22 02:57:25": [
        {
            "position": "1",
            "titre": "the",
            "taches": [
                {
                    "text": "lutwrld",
                    "date": "",
                    "debut": "",
                    "fin": "",
                    "etat": "init",
                    "parent": "1"
                },
                {
                    "text": "is",
                    "date": "",
                    "debut": "",
                    "fin": "",
                    "etat": "init",
                    "parent": "1"
                },
                {
                    "text": "the ",
                    "date": "",
                    "debut": "",
                    "fin": "",
                    "etat": "init",
                    "parent": "1"
                },
                {
                    "text": "best\n",
                    "date": "",
                    "debut": "",
                    "fin": "",
                    "etat": "init",
                    "parent": "1"
                },
                {
                    "text": "bets kolomo cjio sko dsko dsok dsok squyb squ qucn cuqc cqun az ez ic cqi cqi cqijc cqijc cqijc cqij cqnjicq cj",
                    "date": "",
                    "debut": "",
                    "fin": "",
                    "etat": "init",
                    "parent": "1"
                },
                {
                    "text": "k,sd ock cxu xl,c qun",
                    "date": "",
                    "debut": "",
                    "fin": "",
                    "etat": "init",
                    "parent": "1"
                }
            ]
        },
        {
            "position": "2",
            "titre": "end",
            "taches": [
                {
                    "text": "ko",
                    "date": "2022-04-04",
                    "debut": "07:12",
                    "fin": "07:13",
                    "etat": "termine",
                    "parent": "2"
                }
            ]
        },
        {
            "position": "3",
            "titre": "|^^|",
            "taches": []
        },
        [
            {
                "text": "lang",
                "date": "2022-04-04",
                "debut": "10:00",
                "fin": "10:05",
                "etat": "init",
                "parent": "1"
            },
            {
                "text": "nice",
                "date": "",
                "debut": "",
                "fin": "",
                "etat": "init",
                "parent": "2"
            },
            {
                "text": "lut wrld is going good",
                "date": "2022-04-04",
                "debut": "12:00",
                "fin": "15:09",
                "etat": "init",
                "parent": "3"
            },
            {
                "text": "lutwrld",
                "date": "2022-04-04",
                "debut": "12:00",
                "fin": "13:00",
                "etat": "init",
                "parent": "1"
            },
            {
                "text": "is",
                "date": "",
                "debut": "",
                "fin": "",
                "etat": "init",
                "parent": "2"
            },
            {
                "text": "wrld",
                "date": "",
                "debut": "",
                "fin": "",
                "etat": "init",
                "parent": "3"
            },
            {
                "text": "lorem ipsum for lut",
                "date": "",
                "debut": "",
                "fin": "",
                "etat": "init",
                "parent": "1"
            },
            {
                "text": "wey",
                "date": "",
                "debut": "",
                "fin": "",
                "etat": "init",
                "parent": "1"
            }
        ]
    ],
    "09-04-22 02:57:43": [
        {
            "position": "1",
            "titre": "the",
            "taches": [
                {
                    "text": "lutwrld",
                    "date": "",
                    "debut": "",
                    "fin": "",
                    "etat": "init",
                    "parent": "1"
                },
                {
                    "text": "is",
                    "date": "",
                    "debut": "",
                    "fin": "",
                    "etat": "init",
                    "parent": "1"
                },
                {
                    "text": "the ",
                    "date": "",
                    "debut": "",
                    "fin": "",
                    "etat": "init",
                    "parent": "1"
                },
                {
                    "text": "best\n",
                    "date": "",
                    "debut": "",
                    "fin": "",
                    "etat": "init",
                    "parent": "1"
                },
                {
                    "text": "bets kolomo cjio sko dsko dsok dsok squyb squ qucn cuqc cqun az ez ic cqi cqi cqijc cqijc cqijc cqij cqnjicq cj",
                    "date": "",
                    "debut": "",
                    "fin": "",
                    "etat": "init",
                    "parent": "1"
                },
                {
                    "text": "k,sd ock cxu xl,c qun",
                    "date": "",
                    "debut": "",
                    "fin": "",
                    "etat": "init",
                    "parent": "1"
                },
                {
                    "text": "lutwrld",
                    "date": "2022-04-04",
                    "debut": "12:00",
                    "fin": "13:00",
                    "etat": "init",
                    "parent": "1"
                }
            ]
        },
        {
            "position": "2",
            "titre": "end",
            "taches": [
                {
                    "text": "ko",
                    "date": "2022-04-04",
                    "debut": "07:12",
                    "fin": "07:13",
                    "etat": "termine",
                    "parent": "2"
                },
                {
                    "text": "is",
                    "date": "",
                    "debut": "",
                    "fin": "",
                    "etat": "init",
                    "parent": "2"
                }
            ]
        },
        {
            "position": "3",
            "titre": "|^^|",
            "taches": [
                {
                    "text": "wrld",
                    "date": "",
                    "debut": "",
                    "fin": "",
                    "etat": "init",
                    "parent": "3"
                }
            ]
        },
        [
            {
                "text": "lang",
                "date": "2022-04-04",
                "debut": "10:00",
                "fin": "10:05",
                "etat": "init",
                "parent": "1"
            },
            {
                "text": "nice",
                "date": "",
                "debut": "",
                "fin": "",
                "etat": "init",
                "parent": "2"
            },
            {
                "text": "lut wrld is going good",
                "date": "2022-04-04",
                "debut": "12:00",
                "fin": "15:09",
                "etat": "init",
                "parent": "3"
            },
            {
                "text": "lorem ipsum for lut",
                "date": "",
                "debut": "",
                "fin": "",
                "etat": "init",
                "parent": "1"
            },
            {
                "text": "wey",
                "date": "",
                "debut": "",
                "fin": "",
                "etat": "init",
                "parent": "1"
            }
        ]
    ],
    "11-04-22 06:06:06": [
        {
            "position": "1",
            "titre": "end",
            "taches": [
                {
                    "text": "bets kolomo cjio sko dsko dsok dsok squyb squ qucn cuqc cqun az ez ic cqi cqi cqijc cqijc cqijc cqij cqnjicq cj",
                    "date": "",
                    "debut": "",
                    "fin": "",
                    "etat": "init",
                    "parent": "1"
                }
            ]
        },
        [
            {
                "text": "lang",
                "date": "2022-04-04",
                "debut": "10:00",
                "fin": "10:05",
                "etat": "init",
                "parent": "1"
            },
            {
                "text": "nice",
                "date": "",
                "debut": "",
                "fin": "",
                "etat": "init",
                "parent": "2"
            },
            {
                "text": "lut wrld is going good",
                "date": "2022-04-04",
                "debut": "12:00",
                "fin": "15:09",
                "etat": "init",
                "parent": "3"
            },
            {
                "text": "lorem ipsum for lut",
                "date": "",
                "debut": "",
                "fin": "",
                "etat": "init",
                "parent": "1"
            },
            {
                "text": "wey",
                "date": "",
                "debut": "",
                "fin": "",
                "etat": "init",
                "parent": "1"
            }
        ]
    ],
    "22-04-22 12:02:59": [
        {
            "position": "1",
            "titre": "the",
            "taches": [
                {
                    "text": "lutwrld",
                    "date": "",
                    "debut": "",
                    "fin": "",
                    "etat": "init",
                    "parent": "1"
                },
                {
                    "text": "the ",
                    "date": "",
                    "debut": "",
                    "fin": "",
                    "etat": "init",
                    "parent": "1"
                },
                {
                    "text": "best\n",
                    "date": "",
                    "debut": "",
                    "fin": "",
                    "etat": "init",
                    "parent": "1"
                },
                {
                    "text": "bets kolomo cjio sko dsko dsok dsok squyb squ qucn cuqc cqun az ez ic cqi cqi cqijc cqijc cqijc cqij cqnjicq cj",
                    "date": "",
                    "debut": "",
                    "fin": "",
                    "etat": "init",
                    "parent": "1"
                },
                {
                    "text": "k,sd ock cxu xl,c qun",
                    "date": "",
                    "debut": "",
                    "fin": "",
                    "etat": "init",
                    "parent": "1"
                },
                {
                    "text": "lutwrld",
                    "date": "2022-04-04",
                    "debut": "12:00",
                    "fin": "13:00",
                    "etat": "init",
                    "parent": "1"
                },
                {
                    "text": "lang",
                    "date": "2022-04-04",
                    "debut": "10:00",
                    "fin": "10:05",
                    "etat": "init",
                    "parent": "1"
                }
            ]
        },
        {
            "position": "2",
            "titre": "end",
            "taches": [
                {
                    "text": "ko",
                    "date": "2022-04-04",
                    "debut": "07:12",
                    "fin": "07:13",
                    "etat": "termine",
                    "parent": "2"
                },
                {
                    "text": "is",
                    "date": "",
                    "debut": "",
                    "fin": "",
                    "etat": "init",
                    "parent": "2"
                },
                {
                    "text": "is",
                    "date": "",
                    "debut": "",
                    "fin": "",
                    "etat": "init",
                    "parent": "2"
                }
            ]
        },
        {
            "position": "3",
            "titre": "|^^|",
            "taches": [
                {
                    "text": "wrld",
                    "date": "",
                    "debut": "",
                    "fin": "",
                    "etat": "init",
                    "parent": "3"
                },
                {
                    "text": "lut wrld is going good",
                    "date": "2022-04-04",
                    "debut": "12:00",
                    "fin": "15:09",
                    "etat": "init",
                    "parent": "3"
                }
            ]
        },
        {
            "position": "4",
            "titre": "Column 4",
            "taches": []
        },
        [
            {
                "text": "nice",
                "date": "",
                "debut": "",
                "fin": "",
                "etat": "init",
                "parent": "2"
            },
            {
                "text": "lorem ipsum for lut",
                "date": "",
                "debut": "",
                "fin": "",
                "etat": "init",
                "parent": "1"
            },
            {
                "text": "wey",
                "date": "",
                "debut": "",
                "fin": "",
                "etat": "init",
                "parent": "1"
            }
        ]
    ],
    "22-04-22 12:07:58": [
        {
            "position": "1",
            "titre": "the",
            "taches": [
                {
                    "text": "lutwrld",
                    "date": "",
                    "debut": "",
                    "fin": "",
                    "etat": "init",
                    "parent": "1"
                },
                {
                    "text": "the ",
                    "date": "",
                    "debut": "",
                    "fin": "",
                    "etat": "init",
                    "parent": "1"
                },
                {
                    "text": "best\n",
                    "date": "",
                    "debut": "",
                    "fin": "",
                    "etat": "init",
                    "parent": "1"
                },
                {
                    "text": "bets kolomo cjio sko dsko dsok dsok squyb squ qucn cuqc cqun az ez ic cqi cqi cqijc cqijc cqijc cqij cqnjicq cj",
                    "date": "",
                    "debut": "",
                    "fin": "",
                    "etat": "init",
                    "parent": "1"
                },
                {
                    "text": "k,sd ock cxu xl,c qun",
                    "date": "",
                    "debut": "",
                    "fin": "",
                    "etat": "init",
                    "parent": "1"
                },
                {
                    "text": "lutwrld",
                    "date": "2022-04-04",
                    "debut": "12:00",
                    "fin": "13:00",
                    "etat": "init",
                    "parent": "1"
                },
                {
                    "text": "lang",
                    "date": "2022-04-04",
                    "debut": "10:00",
                    "fin": "10:05",
                    "etat": "init",
                    "parent": "1"
                }
            ]
        },
        {
            "position": "2",
            "titre": "end",
            "taches": [
                {
                    "text": "ko",
                    "date": "2022-04-04",
                    "debut": "07:12",
                    "fin": "07:13",
                    "etat": "termine",
                    "parent": "2"
                },
                {
                    "text": "is",
                    "date": "",
                    "debut": "",
                    "fin": "",
                    "etat": "init",
                    "parent": "2"
                },
                {
                    "text": "is",
                    "date": "",
                    "debut": "",
                    "fin": "",
                    "etat": "init",
                    "parent": "2"
                }
            ]
        },
        {
            "position": "3",
            "titre": "|^^|",
            "taches": [
                {
                    "text": "wrld",
                    "date": "",
                    "debut": "",
                    "fin": "",
                    "etat": "init",
                    "parent": "3"
                },
                {
                    "text": "lut wrld is going good",
                    "date": "2022-04-04",
                    "debut": "12:00",
                    "fin": "15:09",
                    "etat": "init",
                    "parent": "3"
                }
            ]
        },
        {
            "position": "4",
            "titre": "Column 4",
            "taches": []
        },
        [
            {
                "text": "nice",
                "date": "",
                "debut": "",
                "fin": "",
                "etat": "init",
                "parent": "2"
            },
            {
                "text": "lorem ipsum for lut",
                "date": "",
                "debut": "",
                "fin": "",
                "etat": "init",
                "parent": "1"
            },
            {
                "text": "wey",
                "date": "",
                "debut": "",
                "fin": "",
                "etat": "init",
                "parent": "1"
            }
        ]
    ]
}